outline_sdk/__init__.py
outline_sdk/client.py
outline_sdk/exceptions.py
outline_sdk/service.py
outline_sdk/struct.py
outline_sdk-0.2.0.dist-info/WHEEL
outline_sdk-0.2.0.dist-info/METADATA
outline_sdk-0.2.0.dist-info/RECORD
