Metadata-Version: 2.1
Name: outline-sdk
Version: 0.2.0
Summary: Async Python SDK wrapper for Outline Manager VPN
Home-page: https://github.com/skar404/outline-sdk
License: MIT
Author: Denis Malin
Author-email: denis@malina.page
Requires-Python: >=3.11,<4.0
Classifier: License :: OSI Approved :: MIT License
Classifier: Programming Language :: Python :: 3
Classifier: Programming Language :: Python :: 3.11
Requires-Dist: aio-clients (>=2.0.0,<3.0.0)
Requires-Dist: pyrogram (>=2.0.106,<3.0.0)
Requires-Dist: uvloop (>=0.17.0,<0.18.0)
Project-URL: Documentation, https://github.com/skar404/outline-sdk
Project-URL: Repository, https://github.com/skar404/outline-sdk
